{"page":191,"lines":[{"line":1,"type":"ayah","centered":false,"words":[{"sura":9,"aya":27,"word_idxs":[0],"glyph":"ﭑ","uthmani":"ثُمَّ"},{"sura":9,"aya":27,"word_idxs":[1],"glyph":"ﭒ","uthmani":"يَتُوبُ"},{"sura":9,"aya":27,"word_idxs":[2],"glyph":"ﭓ","uthmani":"ٱللَّهُ"},{"sura":9,"aya":27,"word_idxs":[3],"glyph":"ﭔ","uthmani":"مِنۢ"},{"sura":9,"aya":27,"word_idxs":[4],"glyph":"ﭕ","uthmani":"بَعْدِ"},{"sura":9,"aya":27,"word_idxs":[5],"glyph":"ﭖ","uthmani":"ذَٰلِكَ"},{"sura":9,"aya":27,"word_idxs":[6],"glyph":"ﭗ","uthmani":"عَلَىٰ"},{"sura":9,"aya":27,"word_idxs":[7],"glyph":"ﭘ","uthmani":"مَن"},{"sura":9,"aya":27,"word_idxs":[8],"glyph":"ﭙﭚ","uthmani":"يَشَآءُ"},{"sura":9,"aya":27,"word_idxs":[9],"glyph":"ﭛ","uthmani":"وَٱللَّهُ"},{"sura":9,"aya":27,"word_idxs":[10],"glyph":"ﭜ","uthmani":"غَفُورٌۭ"}]},{"line":2,"type":"ayah","centered":false,"words":[{"sura":9,"aya":27,"word_idxs":[11],"glyph":"ﭝ","uthmani":"رَّحِيمٌۭ"},{"sura":9,"aya":27,"word_idxs":[],"glyph":"ﭞ","uthmani":""},{"sura":9,"aya":28,"word_idxs":[0],"glyph":"ﭟ","uthmani":"يَـٰٓأَيُّهَا"},{"sura":9,"aya":28,"word_idxs":[1],"glyph":"ﭠ","uthmani":"ٱلَّذِينَ"},{"sura":9,"aya":28,"word_idxs":[2],"glyph":"ﭡ","uthmani":"ءَامَنُوٓا۟"},{"sura":9,"aya":28,"word_idxs":[3],"glyph":"ﭢ","uthmani":"إِنَّمَا"},{"sura":9,"aya":28,"word_idxs":[4],"glyph":"ﭣ","uthmani":"ٱلْمُشْرِكُونَ"}]},{"line":3,"type":"ayah","centered":false,"words":[{"sura":9,"aya":28,"word_idxs":[5],"glyph":"ﭤ","uthmani":"نَجَسٌۭ"},{"sura":9,"aya":28,"word_idxs":[6],"glyph":"ﭥ","uthmani":"فَلَا"},{"sura":9,"aya":28,"word_idxs":[7],"glyph":"ﭦ","uthmani":"يَقْرَبُوا۟"},{"sura":9,"aya":28,"word_idxs":[8],"glyph":"ﭧ","uthmani":"ٱلْمَسْجِدَ"},{"sura":9,"aya":28,"word_idxs":[9],"glyph":"ﭨ","uthmani":"ٱلْحَرَامَ"},{"sura":9,"aya":28,"word_idxs":[10],"glyph":"ﭩ","uthmani":"بَعْدَ"},{"sura":9,"aya":28,"word_idxs":[11],"glyph":"ﭪ","uthmani":"عَامِهِمْ"},{"sura":9,"aya":28,"word_idxs":[12],"glyph":"ﭫﭬ","uthmani":"هَـٰذَا"}]},{"line":4,"type":"ayah","centered":false,"words":[{"sura":9,"aya":28,"word_idxs":[13],"glyph":"ﭭ","uthmani":"وَإِنْ"},{"sura":9,"aya":28,"word_idxs":[14],"glyph":"ﭮ","uthmani":"خِفْتُمْ"},{"sura":9,"aya":28,"word_idxs":[15],"glyph":"ﭯ","uthmani":"عَيْلَةًۭ"},{"sura":9,"aya":28,"word_idxs":[16],"glyph":"ﭰ","uthmani":"فَسَوْفَ"},{"sura":9,"aya":28,"word_idxs":[17],"glyph":"ﭱ","uthmani":"يُغْنِيكُمُ"},{"sura":9,"aya":28,"word_idxs":[18],"glyph":"ﭲ","uthmani":"ٱللَّهُ"},{"sura":9,"aya":28,"word_idxs":[19],"glyph":"ﭳ","uthmani":"مِن"},{"sura":9,"aya":28,"word_idxs":[20],"glyph":"ﭴ","uthmani":"فَضْلِهِۦٓ"},{"sura":9,"aya":28,"word_idxs":[21],"glyph":"ﭵ","uthmani":"إِن"}]},{"line":5,"type":"ayah","centered":false,"words":[{"sura":9,"aya":28,"word_idxs":[22],"glyph":"ﭶﭷ","uthmani":"شَآءَ"},{"sura":9,"aya":28,"word_idxs":[23],"glyph":"ﭸ","uthmani":"إِنَّ"},{"sura":9,"aya":28,"word_idxs":[24],"glyph":"ﭹ","uthmani":"ٱللَّهَ"},{"sura":9,"aya":28,"word_idxs":[25],"glyph":"ﭺ","uthmani":"عَلِيمٌ"},{"sura":9,"aya":28,"word_idxs":[26],"glyph":"ﭻ","uthmani":"حَكِيمٌۭ"},{"sura":9,"aya":28,"word_idxs":[],"glyph":"ﭼ","uthmani":""},{"sura":9,"aya":29,"word_idxs":[0],"glyph":"ﭽ","uthmani":"قَـٰتِلُوا۟"},{"sura":9,"aya":29,"word_idxs":[1],"glyph":"ﭾ","uthmani":"ٱلَّذِينَ"}]},{"line":6,"type":"ayah","centered":false,"words":[{"sura":9,"aya":29,"word_idxs":[2],"glyph":"ﭿ","uthmani":"لَا"},{"sura":9,"aya":29,"word_idxs":[3],"glyph":"ﮀ","uthmani":"يُؤْمِنُونَ"},{"sura":9,"aya":29,"word_idxs":[4],"glyph":"ﮁ","uthmani":"بِٱللَّهِ"},{"sura":9,"aya":29,"word_idxs":[5],"glyph":"ﮂ","uthmani":"وَلَا"},{"sura":9,"aya":29,"word_idxs":[6],"glyph":"ﮃ","uthmani":"بِٱلْيَوْمِ"},{"sura":9,"aya":29,"word_idxs":[7],"glyph":"ﮄ","uthmani":"ٱلْـَٔاخِرِ"},{"sura":9,"aya":29,"word_idxs":[8],"glyph":"ﮅ","uthmani":"وَلَا"},{"sura":9,"aya":29,"word_idxs":[9],"glyph":"ﮆ","uthmani":"يُحَرِّمُونَ"},{"sura":9,"aya":29,"word_idxs":[10],"glyph":"ﮇ","uthmani":"مَا"},{"sura":9,"aya":29,"word_idxs":[11],"glyph":"ﮈ","uthmani":"حَرَّمَ"}]},{"line":7,"type":"ayah","centered":false,"words":[{"sura":9,"aya":29,"word_idxs":[12],"glyph":"ﮉ","uthmani":"ٱللَّهُ"},{"sura":9,"aya":29,"word_idxs":[13],"glyph":"ﮊ","uthmani":"وَرَسُولُهُۥ"},{"sura":9,"aya":29,"word_idxs":[14],"glyph":"ﮋ","uthmani":"وَلَا"},{"sura":9,"aya":29,"word_idxs":[15],"glyph":"ﮌ","uthmani":"يَدِينُونَ"},{"sura":9,"aya":29,"word_idxs":[16],"glyph":"ﮍ","uthmani":"دِينَ"},{"sura":9,"aya":29,"word_idxs":[17],"glyph":"ﮎ","uthmani":"ٱلْحَقِّ"},{"sura":9,"aya":29,"word_idxs":[18],"glyph":"ﮏ","uthmani":"مِنَ"},{"sura":9,"aya":29,"word_idxs":[19],"glyph":"ﮐ","uthmani":"ٱلَّذِينَ"},{"sura":9,"aya":29,"word_idxs":[20],"glyph":"ﮑ","uthmani":"أُوتُوا۟"}]},{"line":8,"type":"ayah","centered":false,"words":[{"sura":9,"aya":29,"word_idxs":[21],"glyph":"ﮒ","uthmani":"ٱلْكِتَـٰبَ"},{"sura":9,"aya":29,"word_idxs":[22],"glyph":"ﮓ","uthmani":"حَتَّىٰ"},{"sura":9,"aya":29,"word_idxs":[23],"glyph":"ﮔ","uthmani":"يُعْطُوا۟"},{"sura":9,"aya":29,"word_idxs":[24],"glyph":"ﮕ","uthmani":"ٱلْجِزْيَةَ"},{"sura":9,"aya":29,"word_idxs":[25],"glyph":"ﮖ","uthmani":"عَن"},{"sura":9,"aya":29,"word_idxs":[26],"glyph":"ﮗ","uthmani":"يَدٍۢ"},{"sura":9,"aya":29,"word_idxs":[27],"glyph":"ﮘ","uthmani":"وَهُمْ"},{"sura":9,"aya":29,"word_idxs":[28],"glyph":"ﮙ","uthmani":"صَـٰغِرُونَ"}]},{"line":9,"type":"ayah","centered":false,"words":[{"sura":9,"aya":29,"word_idxs":[],"glyph":"ﮚ","uthmani":""},{"sura":9,"aya":30,"word_idxs":[0],"glyph":"ﮛ","uthmani":"وَقَالَتِ"},{"sura":9,"aya":30,"word_idxs":[1],"glyph":"ﮜ","uthmani":"ٱلْيَهُودُ"},{"sura":9,"aya":30,"word_idxs":[2],"glyph":"ﮝ","uthmani":"عُزَيْرٌ"},{"sura":9,"aya":30,"word_idxs":[3],"glyph":"ﮞ","uthmani":"ٱبْنُ"},{"sura":9,"aya":30,"word_idxs":[4],"glyph":"ﮟ","uthmani":"ٱللَّهِ"},{"sura":9,"aya":30,"word_idxs":[5],"glyph":"ﮠ","uthmani":"وَقَالَتِ"},{"sura":9,"aya":30,"word_idxs":[6],"glyph":"ﮡ","uthmani":"ٱلنَّصَـٰرَى"}]},{"line":10,"type":"ayah","centered":false,"words":[{"sura":9,"aya":30,"word_idxs":[7],"glyph":"ﮢ","uthmani":"ٱلْمَسِيحُ"},{"sura":9,"aya":30,"word_idxs":[8],"glyph":"ﮣ","uthmani":"ٱبْنُ"},{"sura":9,"aya":30,"word_idxs":[9],"glyph":"ﮤﮥ","uthmani":"ٱللَّهِ"},{"sura":9,"aya":30,"word_idxs":[10],"glyph":"ﮦ","uthmani":"ذَٰلِكَ"},{"sura":9,"aya":30,"word_idxs":[11],"glyph":"ﮧ","uthmani":"قَوْلُهُم"},{"sura":9,"aya":30,"word_idxs":[12],"glyph":"ﮨﮩ","uthmani":"بِأَفْوَٰهِهِمْ"}]},{"line":11,"type":"ayah","centered":false,"words":[{"sura":9,"aya":30,"word_idxs":[13],"glyph":"ﮪ","uthmani":"يُضَـٰهِـُٔونَ"},{"sura":9,"aya":30,"word_idxs":[14],"glyph":"ﮫ","uthmani":"قَوْلَ"},{"sura":9,"aya":30,"word_idxs":[15],"glyph":"ﮬ","uthmani":"ٱلَّذِينَ"},{"sura":9,"aya":30,"word_idxs":[16],"glyph":"ﮭ","uthmani":"كَفَرُوا۟"},{"sura":9,"aya":30,"word_idxs":[17],"glyph":"ﮮ","uthmani":"مِن"},{"sura":9,"aya":30,"word_idxs":[18],"glyph":"ﮯﮰ","uthmani":"قَبْلُ"},{"sura":9,"aya":30,"word_idxs":[19],"glyph":"ﮱ","uthmani":"قَـٰتَلَهُمُ"}]},{"line":12,"type":"ayah","centered":false,"words":[{"sura":9,"aya":30,"word_idxs":[20],"glyph":"ﯓﯔ","uthmani":"ٱللَّهُ"},{"sura":9,"aya":30,"word_idxs":[21],"glyph":"ﯕ","uthmani":"أَنَّىٰ"},{"sura":9,"aya":30,"word_idxs":[22],"glyph":"ﯖ","uthmani":"يُؤْفَكُونَ"},{"sura":9,"aya":30,"word_idxs":[],"glyph":"ﯗ","uthmani":""},{"sura":9,"aya":31,"word_idxs":[0],"glyph":"ﯘ","uthmani":"ٱتَّخَذُوٓا۟"},{"sura":9,"aya":31,"word_idxs":[1],"glyph":"ﯙ","uthmani":"أَحْبَارَهُمْ"}]},{"line":13,"type":"ayah","centered":false,"words":[{"sura":9,"aya":31,"word_idxs":[2],"glyph":"ﯚ","uthmani":"وَرُهْبَـٰنَهُمْ"},{"sura":9,"aya":31,"word_idxs":[3],"glyph":"ﯛ","uthmani":"أَرْبَابًۭا"},{"sura":9,"aya":31,"word_idxs":[4],"glyph":"ﯜ","uthmani":"مِّن"},{"sura":9,"aya":31,"word_idxs":[5],"glyph":"ﯝ","uthmani":"دُونِ"},{"sura":9,"aya":31,"word_idxs":[6],"glyph":"ﯞ","uthmani":"ٱللَّهِ"},{"sura":9,"aya":31,"word_idxs":[7],"glyph":"ﯟ","uthmani":"وَٱلْمَسِيحَ"},{"sura":9,"aya":31,"word_idxs":[8],"glyph":"ﯠ","uthmani":"ٱبْنَ"}]},{"line":14,"type":"ayah","centered":false,"words":[{"sura":9,"aya":31,"word_idxs":[9],"glyph":"ﯡ","uthmani":"مَرْيَمَ"},{"sura":9,"aya":31,"word_idxs":[10],"glyph":"ﯢ","uthmani":"وَمَآ"},{"sura":9,"aya":31,"word_idxs":[11],"glyph":"ﯣ","uthmani":"أُمِرُوٓا۟"},{"sura":9,"aya":31,"word_idxs":[12],"glyph":"ﯤ","uthmani":"إِلَّا"},{"sura":9,"aya":31,"word_idxs":[13],"glyph":"ﯥ","uthmani":"لِيَعْبُدُوٓا۟"},{"sura":9,"aya":31,"word_idxs":[14],"glyph":"ﯦ","uthmani":"إِلَـٰهًۭا"},{"sura":9,"aya":31,"word_idxs":[15],"glyph":"ﯧﯨ","uthmani":"وَٰحِدًۭا"}]},{"line":15,"type":"ayah","centered":false,"words":[{"sura":9,"aya":31,"word_idxs":[16],"glyph":"ﯩ","uthmani":"لَّآ"},{"sura":9,"aya":31,"word_idxs":[17],"glyph":"ﯪ","uthmani":"إِلَـٰهَ"},{"sura":9,"aya":31,"word_idxs":[18],"glyph":"ﯫ","uthmani":"إِلَّا"},{"sura":9,"aya":31,"word_idxs":[19],"glyph":"ﯬﯭ","uthmani":"هُوَ"},{"sura":9,"aya":31,"word_idxs":[20],"glyph":"ﯮ","uthmani":"سُبْحَـٰنَهُۥ"},{"sura":9,"aya":31,"word_idxs":[21],"glyph":"ﯯ","uthmani":"عَمَّا"},{"sura":9,"aya":31,"word_idxs":[22],"glyph":"ﯰ","uthmani":"يُشْرِكُونَ"},{"sura":9,"aya":31,"word_idxs":[],"glyph":"ﯱ","uthmani":""}]}],"suras":[9]}