{"page":266,"lines":[{"line":1,"type":"ayah","centered":false,"words":[{"sura":15,"aya":71,"word_idxs":[0],"glyph":"ﭑ","uthmani":"قَالَ"},{"sura":15,"aya":71,"word_idxs":[1],"glyph":"ﭒ","uthmani":"هَـٰٓؤُلَآءِ"},{"sura":15,"aya":71,"word_idxs":[2],"glyph":"ﭓ","uthmani":"بَنَاتِىٓ"},{"sura":15,"aya":71,"word_idxs":[3],"glyph":"ﭔ","uthmani":"إِن"},{"sura":15,"aya":71,"word_idxs":[4],"glyph":"ﭕ","uthmani":"كُنتُمْ"},{"sura":15,"aya":71,"word_idxs":[5],"glyph":"ﭖ","uthmani":"فَـٰعِلِينَ"},{"sura":15,"aya":71,"word_idxs":[],"glyph":"ﭗ","uthmani":""},{"sura":15,"aya":72,"word_idxs":[0],"glyph":"ﭘ","uthmani":"لَعَمْرُكَ"},{"sura":15,"aya":72,"word_idxs":[1],"glyph":"ﭙ","uthmani":"إِنَّهُمْ"},{"sura":15,"aya":72,"word_idxs":[2],"glyph":"ﭚ","uthmani":"لَفِى"},{"sura":15,"aya":72,"word_idxs":[3],"glyph":"ﭛ","uthmani":"سَكْرَتِهِمْ"}]},{"line":2,"type":"ayah","centered":false,"words":[{"sura":15,"aya":72,"word_idxs":[4],"glyph":"ﭜ","uthmani":"يَعْمَهُونَ"},{"sura":15,"aya":72,"word_idxs":[],"glyph":"ﭝ","uthmani":""},{"sura":15,"aya":73,"word_idxs":[0],"glyph":"ﭞ","uthmani":"فَأَخَذَتْهُمُ"},{"sura":15,"aya":73,"word_idxs":[1],"glyph":"ﭟ","uthmani":"ٱلصَّيْحَةُ"},{"sura":15,"aya":73,"word_idxs":[2],"glyph":"ﭠ","uthmani":"مُشْرِقِينَ"},{"sura":15,"aya":73,"word_idxs":[],"glyph":"ﭡ","uthmani":""},{"sura":15,"aya":74,"word_idxs":[0],"glyph":"ﭢ","uthmani":"فَجَعَلْنَا"},{"sura":15,"aya":74,"word_idxs":[1],"glyph":"ﭣ","uthmani":"عَـٰلِيَهَا"}]},{"line":3,"type":"ayah","centered":false,"words":[{"sura":15,"aya":74,"word_idxs":[2],"glyph":"ﭤ","uthmani":"سَافِلَهَا"},{"sura":15,"aya":74,"word_idxs":[3],"glyph":"ﭥ","uthmani":"وَأَمْطَرْنَا"},{"sura":15,"aya":74,"word_idxs":[4],"glyph":"ﭦ","uthmani":"عَلَيْهِمْ"},{"sura":15,"aya":74,"word_idxs":[5],"glyph":"ﭧ","uthmani":"حِجَارَةًۭ"},{"sura":15,"aya":74,"word_idxs":[6],"glyph":"ﭨ","uthmani":"مِّن"},{"sura":15,"aya":74,"word_idxs":[7],"glyph":"ﭩ","uthmani":"سِجِّيلٍ"},{"sura":15,"aya":74,"word_idxs":[],"glyph":"ﭪ","uthmani":""},{"sura":15,"aya":75,"word_idxs":[0],"glyph":"ﭫ","uthmani":"إِنَّ"},{"sura":15,"aya":75,"word_idxs":[1],"glyph":"ﭬ","uthmani":"فِى"},{"sura":15,"aya":75,"word_idxs":[2],"glyph":"ﭭ","uthmani":"ذَٰلِكَ"}]},{"line":4,"type":"ayah","centered":false,"words":[{"sura":15,"aya":75,"word_idxs":[3],"glyph":"ﭮ","uthmani":"لَـَٔايَـٰتٍۢ"},{"sura":15,"aya":75,"word_idxs":[4],"glyph":"ﭯ","uthmani":"لِّلْمُتَوَسِّمِينَ"},{"sura":15,"aya":75,"word_idxs":[],"glyph":"ﭰ","uthmani":""},{"sura":15,"aya":76,"word_idxs":[0],"glyph":"ﭱ","uthmani":"وَإِنَّهَا"},{"sura":15,"aya":76,"word_idxs":[1],"glyph":"ﭲ","uthmani":"لَبِسَبِيلٍۢ"},{"sura":15,"aya":76,"word_idxs":[2],"glyph":"ﭳ","uthmani":"مُّقِيمٍ"},{"sura":15,"aya":76,"word_idxs":[],"glyph":"ﭴ","uthmani":""},{"sura":15,"aya":77,"word_idxs":[0],"glyph":"ﭵ","uthmani":"إِنَّ"},{"sura":15,"aya":77,"word_idxs":[1],"glyph":"ﭶ","uthmani":"فِى"},{"sura":15,"aya":77,"word_idxs":[2],"glyph":"ﭷ","uthmani":"ذَٰلِكَ"}]},{"line":5,"type":"ayah","centered":false,"words":[{"sura":15,"aya":77,"word_idxs":[3],"glyph":"ﭸ","uthmani":"لَـَٔايَةًۭ"},{"sura":15,"aya":77,"word_idxs":[4],"glyph":"ﭹ","uthmani":"لِّلْمُؤْمِنِينَ"},{"sura":15,"aya":77,"word_idxs":[],"glyph":"ﭺ","uthmani":""},{"sura":15,"aya":78,"word_idxs":[0],"glyph":"ﭻ","uthmani":"وَإِن"},{"sura":15,"aya":78,"word_idxs":[1],"glyph":"ﭼ","uthmani":"كَانَ"},{"sura":15,"aya":78,"word_idxs":[2],"glyph":"ﭽ","uthmani":"أَصْحَـٰبُ"},{"sura":15,"aya":78,"word_idxs":[3],"glyph":"ﭾ","uthmani":"ٱلْأَيْكَةِ"},{"sura":15,"aya":78,"word_idxs":[4],"glyph":"ﭿ","uthmani":"لَظَـٰلِمِينَ"},{"sura":15,"aya":78,"word_idxs":[],"glyph":"ﮀ","uthmani":""}]},{"line":6,"type":"ayah","centered":false,"words":[{"sura":15,"aya":79,"word_idxs":[0],"glyph":"ﮁ","uthmani":"فَٱنتَقَمْنَا"},{"sura":15,"aya":79,"word_idxs":[1],"glyph":"ﮂ","uthmani":"مِنْهُمْ"},{"sura":15,"aya":79,"word_idxs":[2],"glyph":"ﮃ","uthmani":"وَإِنَّهُمَا"},{"sura":15,"aya":79,"word_idxs":[3],"glyph":"ﮄ","uthmani":"لَبِإِمَامٍۢ"},{"sura":15,"aya":79,"word_idxs":[4],"glyph":"ﮅ","uthmani":"مُّبِينٍۢ"},{"sura":15,"aya":79,"word_idxs":[],"glyph":"ﮆ","uthmani":""},{"sura":15,"aya":80,"word_idxs":[0],"glyph":"ﮇ","uthmani":"وَلَقَدْ"},{"sura":15,"aya":80,"word_idxs":[1],"glyph":"ﮈ","uthmani":"كَذَّبَ"},{"sura":15,"aya":80,"word_idxs":[2],"glyph":"ﮉ","uthmani":"أَصْحَـٰبُ"}]},{"line":7,"type":"ayah","centered":false,"words":[{"sura":15,"aya":80,"word_idxs":[3],"glyph":"ﮊ","uthmani":"ٱلْحِجْرِ"},{"sura":15,"aya":80,"word_idxs":[4],"glyph":"ﮋ","uthmani":"ٱلْمُرْسَلِينَ"},{"sura":15,"aya":80,"word_idxs":[],"glyph":"ﮌ","uthmani":""},{"sura":15,"aya":81,"word_idxs":[0],"glyph":"ﮍ","uthmani":"وَءَاتَيْنَـٰهُمْ"},{"sura":15,"aya":81,"word_idxs":[1],"glyph":"ﮎ","uthmani":"ءَايَـٰتِنَا"},{"sura":15,"aya":81,"word_idxs":[2],"glyph":"ﮏ","uthmani":"فَكَانُوا۟"},{"sura":15,"aya":81,"word_idxs":[3],"glyph":"ﮐ","uthmani":"عَنْهَا"},{"sura":15,"aya":81,"word_idxs":[4],"glyph":"ﮑ","uthmani":"مُعْرِضِينَ"}]},{"line":8,"type":"ayah","centered":false,"words":[{"sura":15,"aya":81,"word_idxs":[],"glyph":"ﮒ","uthmani":""},{"sura":15,"aya":82,"word_idxs":[0],"glyph":"ﮓ","uthmani":"وَكَانُوا۟"},{"sura":15,"aya":82,"word_idxs":[1],"glyph":"ﮔ","uthmani":"يَنْحِتُونَ"},{"sura":15,"aya":82,"word_idxs":[2],"glyph":"ﮕ","uthmani":"مِنَ"},{"sura":15,"aya":82,"word_idxs":[3],"glyph":"ﮖ","uthmani":"ٱلْجِبَالِ"},{"sura":15,"aya":82,"word_idxs":[4],"glyph":"ﮗ","uthmani":"بُيُوتًا"},{"sura":15,"aya":82,"word_idxs":[5],"glyph":"ﮘ","uthmani":"ءَامِنِينَ"},{"sura":15,"aya":82,"word_idxs":[],"glyph":"ﮙ","uthmani":""},{"sura":15,"aya":83,"word_idxs":[0],"glyph":"ﮚ","uthmani":"فَأَخَذَتْهُمُ"}]},{"line":9,"type":"ayah","centered":false,"words":[{"sura":15,"aya":83,"word_idxs":[1],"glyph":"ﮛ","uthmani":"ٱلصَّيْحَةُ"},{"sura":15,"aya":83,"word_idxs":[2],"glyph":"ﮜ","uthmani":"مُصْبِحِينَ"},{"sura":15,"aya":83,"word_idxs":[],"glyph":"ﮝ","uthmani":""},{"sura":15,"aya":84,"word_idxs":[0],"glyph":"ﮞ","uthmani":"فَمَآ"},{"sura":15,"aya":84,"word_idxs":[1],"glyph":"ﮟ","uthmani":"أَغْنَىٰ"},{"sura":15,"aya":84,"word_idxs":[2],"glyph":"ﮠ","uthmani":"عَنْهُم"},{"sura":15,"aya":84,"word_idxs":[3],"glyph":"ﮡ","uthmani":"مَّا"},{"sura":15,"aya":84,"word_idxs":[4],"glyph":"ﮢ","uthmani":"كَانُوا۟"},{"sura":15,"aya":84,"word_idxs":[5],"glyph":"ﮣ","uthmani":"يَكْسِبُونَ"},{"sura":15,"aya":84,"word_idxs":[],"glyph":"ﮤ","uthmani":""}]},{"line":10,"type":"ayah","centered":false,"words":[{"sura":15,"aya":85,"word_idxs":[0],"glyph":"ﮥ","uthmani":"وَمَا"},{"sura":15,"aya":85,"word_idxs":[1],"glyph":"ﮦ","uthmani":"خَلَقْنَا"},{"sura":15,"aya":85,"word_idxs":[2],"glyph":"ﮧ","uthmani":"ٱلسَّمَـٰوَٰتِ"},{"sura":15,"aya":85,"word_idxs":[3],"glyph":"ﮨ","uthmani":"وَٱلْأَرْضَ"},{"sura":15,"aya":85,"word_idxs":[4],"glyph":"ﮩ","uthmani":"وَمَا"},{"sura":15,"aya":85,"word_idxs":[5],"glyph":"ﮪ","uthmani":"بَيْنَهُمَآ"},{"sura":15,"aya":85,"word_idxs":[6],"glyph":"ﮫ","uthmani":"إِلَّا"},{"sura":15,"aya":85,"word_idxs":[7],"glyph":"ﮬﮭ","uthmani":"بِٱلْحَقِّ"},{"sura":15,"aya":85,"word_idxs":[8],"glyph":"ﮮ","uthmani":"وَإِنَّ"}]},{"line":11,"type":"ayah","centered":false,"words":[{"sura":15,"aya":85,"word_idxs":[9],"glyph":"ﮯ","uthmani":"ٱلسَّاعَةَ"},{"sura":15,"aya":85,"word_idxs":[10],"glyph":"ﮰﮱ","uthmani":"لَـَٔاتِيَةٌۭ"},{"sura":15,"aya":85,"word_idxs":[11],"glyph":"ﯓ","uthmani":"فَٱصْفَحِ"},{"sura":15,"aya":85,"word_idxs":[12],"glyph":"ﯔ","uthmani":"ٱلصَّفْحَ"},{"sura":15,"aya":85,"word_idxs":[13],"glyph":"ﯕ","uthmani":"ٱلْجَمِيلَ"},{"sura":15,"aya":85,"word_idxs":[],"glyph":"ﯖ","uthmani":""},{"sura":15,"aya":86,"word_idxs":[0],"glyph":"ﯗ","uthmani":"إِنَّ"},{"sura":15,"aya":86,"word_idxs":[1],"glyph":"ﯘ","uthmani":"رَبَّكَ"},{"sura":15,"aya":86,"word_idxs":[2],"glyph":"ﯙ","uthmani":"هُوَ"}]},{"line":12,"type":"ayah","centered":false,"words":[{"sura":15,"aya":86,"word_idxs":[3],"glyph":"ﯚ","uthmani":"ٱلْخَلَّـٰقُ"},{"sura":15,"aya":86,"word_idxs":[4],"glyph":"ﯛ","uthmani":"ٱلْعَلِيمُ"},{"sura":15,"aya":86,"word_idxs":[],"glyph":"ﯜ","uthmani":""},{"sura":15,"aya":87,"word_idxs":[0],"glyph":"ﯝ","uthmani":"وَلَقَدْ"},{"sura":15,"aya":87,"word_idxs":[1],"glyph":"ﯞ","uthmani":"ءَاتَيْنَـٰكَ"},{"sura":15,"aya":87,"word_idxs":[2],"glyph":"ﯟ","uthmani":"سَبْعًۭا"},{"sura":15,"aya":87,"word_idxs":[3],"glyph":"ﯠ","uthmani":"مِّنَ"},{"sura":15,"aya":87,"word_idxs":[4],"glyph":"ﯡ","uthmani":"ٱلْمَثَانِى"},{"sura":15,"aya":87,"word_idxs":[5],"glyph":"ﯢ","uthmani":"وَٱلْقُرْءَانَ"}]},{"line":13,"type":"ayah","centered":false,"words":[{"sura":15,"aya":87,"word_idxs":[6],"glyph":"ﯣ","uthmani":"ٱلْعَظِيمَ"},{"sura":15,"aya":87,"word_idxs":[],"glyph":"ﯤ","uthmani":""},{"sura":15,"aya":88,"word_idxs":[0],"glyph":"ﯥ","uthmani":"لَا"},{"sura":15,"aya":88,"word_idxs":[1],"glyph":"ﯦ","uthmani":"تَمُدَّنَّ"},{"sura":15,"aya":88,"word_idxs":[2],"glyph":"ﯧ","uthmani":"عَيْنَيْكَ"},{"sura":15,"aya":88,"word_idxs":[3],"glyph":"ﯨ","uthmani":"إِلَىٰ"},{"sura":15,"aya":88,"word_idxs":[4],"glyph":"ﯩ","uthmani":"مَا"},{"sura":15,"aya":88,"word_idxs":[5],"glyph":"ﯪ","uthmani":"مَتَّعْنَا"},{"sura":15,"aya":88,"word_idxs":[6],"glyph":"ﯫ","uthmani":"بِهِۦٓ"},{"sura":15,"aya":88,"word_idxs":[7],"glyph":"ﯬ","uthmani":"أَزْوَٰجًۭا"},{"sura":15,"aya":88,"word_idxs":[8],"glyph":"ﯭ","uthmani":"مِّنْهُمْ"}]},{"line":14,"type":"ayah","centered":false,"words":[{"sura":15,"aya":88,"word_idxs":[9],"glyph":"ﯮ","uthmani":"وَلَا"},{"sura":15,"aya":88,"word_idxs":[10],"glyph":"ﯯ","uthmani":"تَحْزَنْ"},{"sura":15,"aya":88,"word_idxs":[11],"glyph":"ﯰ","uthmani":"عَلَيْهِمْ"},{"sura":15,"aya":88,"word_idxs":[12],"glyph":"ﯱ","uthmani":"وَٱخْفِضْ"},{"sura":15,"aya":88,"word_idxs":[13],"glyph":"ﯲ","uthmani":"جَنَاحَكَ"},{"sura":15,"aya":88,"word_idxs":[14],"glyph":"ﯳ","uthmani":"لِلْمُؤْمِنِينَ"},{"sura":15,"aya":88,"word_idxs":[],"glyph":"ﯴ","uthmani":""},{"sura":15,"aya":89,"word_idxs":[0],"glyph":"ﯵ","uthmani":"وَقُلْ"},{"sura":15,"aya":89,"word_idxs":[1],"glyph":"ﯶ","uthmani":"إِنِّىٓ"}]},{"line":15,"type":"ayah","centered":false,"words":[{"sura":15,"aya":89,"word_idxs":[2],"glyph":"ﯷ","uthmani":"أَنَا"},{"sura":15,"aya":89,"word_idxs":[3],"glyph":"ﯸ","uthmani":"ٱلنَّذِيرُ"},{"sura":15,"aya":89,"word_idxs":[4],"glyph":"ﯹ","uthmani":"ٱلْمُبِينُ"},{"sura":15,"aya":89,"word_idxs":[],"glyph":"ﯺ","uthmani":""},{"sura":15,"aya":90,"word_idxs":[0],"glyph":"ﯻ","uthmani":"كَمَآ"},{"sura":15,"aya":90,"word_idxs":[1],"glyph":"ﯼ","uthmani":"أَنزَلْنَا"},{"sura":15,"aya":90,"word_idxs":[2],"glyph":"ﯽ","uthmani":"عَلَى"},{"sura":15,"aya":90,"word_idxs":[3],"glyph":"ﯾ","uthmani":"ٱلْمُقْتَسِمِينَ"},{"sura":15,"aya":90,"word_idxs":[],"glyph":"ﯿ","uthmani":""}]}],"suras":[15]}