{"page":346,"lines":[{"line":1,"type":"ayah","centered":false,"words":[{"sura":23,"aya":60,"word_idxs":[0],"glyph":"ﭑ","uthmani":"وَٱلَّذِينَ"},{"sura":23,"aya":60,"word_idxs":[1],"glyph":"ﭒ","uthmani":"يُؤْتُونَ"},{"sura":23,"aya":60,"word_idxs":[2],"glyph":"ﭓ","uthmani":"مَآ"},{"sura":23,"aya":60,"word_idxs":[3],"glyph":"ﭔ","uthmani":"ءَاتَوا۟"},{"sura":23,"aya":60,"word_idxs":[4],"glyph":"ﭕ","uthmani":"وَّقُلُوبُهُمْ"},{"sura":23,"aya":60,"word_idxs":[5],"glyph":"ﭖ","uthmani":"وَجِلَةٌ"},{"sura":23,"aya":60,"word_idxs":[6],"glyph":"ﭗ","uthmani":"أَنَّهُمْ"},{"sura":23,"aya":60,"word_idxs":[7],"glyph":"ﭘ","uthmani":"إِلَىٰ"},{"sura":23,"aya":60,"word_idxs":[8],"glyph":"ﭙ","uthmani":"رَبِّهِمْ"},{"sura":23,"aya":60,"word_idxs":[9],"glyph":"ﭚ","uthmani":"رَٰجِعُونَ"},{"sura":23,"aya":60,"word_idxs":[],"glyph":"ﭛ","uthmani":""}]},{"line":2,"type":"ayah","centered":false,"words":[{"sura":23,"aya":61,"word_idxs":[0],"glyph":"ﭜ","uthmani":"أُو۟لَـٰٓئِكَ"},{"sura":23,"aya":61,"word_idxs":[1],"glyph":"ﭝ","uthmani":"يُسَـٰرِعُونَ"},{"sura":23,"aya":61,"word_idxs":[2],"glyph":"ﭞ","uthmani":"فِى"},{"sura":23,"aya":61,"word_idxs":[3],"glyph":"ﭟ","uthmani":"ٱلْخَيْرَٰتِ"},{"sura":23,"aya":61,"word_idxs":[4],"glyph":"ﭠ","uthmani":"وَهُمْ"},{"sura":23,"aya":61,"word_idxs":[5],"glyph":"ﭡ","uthmani":"لَهَا"},{"sura":23,"aya":61,"word_idxs":[6],"glyph":"ﭢ","uthmani":"سَـٰبِقُونَ"},{"sura":23,"aya":61,"word_idxs":[],"glyph":"ﭣ","uthmani":""},{"sura":23,"aya":62,"word_idxs":[0],"glyph":"ﭤ","uthmani":"وَلَا"},{"sura":23,"aya":62,"word_idxs":[1],"glyph":"ﭥ","uthmani":"نُكَلِّفُ"}]},{"line":3,"type":"ayah","centered":false,"words":[{"sura":23,"aya":62,"word_idxs":[2],"glyph":"ﭦ","uthmani":"نَفْسًا"},{"sura":23,"aya":62,"word_idxs":[3],"glyph":"ﭧ","uthmani":"إِلَّا"},{"sura":23,"aya":62,"word_idxs":[4],"glyph":"ﭨﭩ","uthmani":"وُسْعَهَا"},{"sura":23,"aya":62,"word_idxs":[5],"glyph":"ﭪ","uthmani":"وَلَدَيْنَا"},{"sura":23,"aya":62,"word_idxs":[6],"glyph":"ﭫ","uthmani":"كِتَـٰبٌۭ"},{"sura":23,"aya":62,"word_idxs":[7],"glyph":"ﭬ","uthmani":"يَنطِقُ"},{"sura":23,"aya":62,"word_idxs":[8],"glyph":"ﭭﭮ","uthmani":"بِٱلْحَقِّ"},{"sura":23,"aya":62,"word_idxs":[9],"glyph":"ﭯ","uthmani":"وَهُمْ"},{"sura":23,"aya":62,"word_idxs":[10],"glyph":"ﭰ","uthmani":"لَا"},{"sura":23,"aya":62,"word_idxs":[11],"glyph":"ﭱ","uthmani":"يُظْلَمُونَ"},{"sura":23,"aya":62,"word_idxs":[],"glyph":"ﭲ","uthmani":""}]},{"line":4,"type":"ayah","centered":false,"words":[{"sura":23,"aya":63,"word_idxs":[0],"glyph":"ﭳ","uthmani":"بَلْ"},{"sura":23,"aya":63,"word_idxs":[1],"glyph":"ﭴ","uthmani":"قُلُوبُهُمْ"},{"sura":23,"aya":63,"word_idxs":[2],"glyph":"ﭵ","uthmani":"فِى"},{"sura":23,"aya":63,"word_idxs":[3],"glyph":"ﭶ","uthmani":"غَمْرَةٍۢ"},{"sura":23,"aya":63,"word_idxs":[4],"glyph":"ﭷ","uthmani":"مِّنْ"},{"sura":23,"aya":63,"word_idxs":[5],"glyph":"ﭸ","uthmani":"هَـٰذَا"},{"sura":23,"aya":63,"word_idxs":[6],"glyph":"ﭹ","uthmani":"وَلَهُمْ"},{"sura":23,"aya":63,"word_idxs":[7],"glyph":"ﭺ","uthmani":"أَعْمَـٰلٌۭ"},{"sura":23,"aya":63,"word_idxs":[8],"glyph":"ﭻ","uthmani":"مِّن"},{"sura":23,"aya":63,"word_idxs":[9],"glyph":"ﭼ","uthmani":"دُونِ"},{"sura":23,"aya":63,"word_idxs":[10],"glyph":"ﭽ","uthmani":"ذَٰلِكَ"},{"sura":23,"aya":63,"word_idxs":[11],"glyph":"ﭾ","uthmani":"هُمْ"},{"sura":23,"aya":63,"word_idxs":[12],"glyph":"ﭿ","uthmani":"لَهَا"}]},{"line":5,"type":"ayah","centered":false,"words":[{"sura":23,"aya":63,"word_idxs":[13],"glyph":"ﮀ","uthmani":"عَـٰمِلُونَ"},{"sura":23,"aya":63,"word_idxs":[],"glyph":"ﮁ","uthmani":""},{"sura":23,"aya":64,"word_idxs":[0],"glyph":"ﮂ","uthmani":"حَتَّىٰٓ"},{"sura":23,"aya":64,"word_idxs":[1],"glyph":"ﮃ","uthmani":"إِذَآ"},{"sura":23,"aya":64,"word_idxs":[2],"glyph":"ﮄ","uthmani":"أَخَذْنَا"},{"sura":23,"aya":64,"word_idxs":[3],"glyph":"ﮅ","uthmani":"مُتْرَفِيهِم"},{"sura":23,"aya":64,"word_idxs":[4],"glyph":"ﮆ","uthmani":"بِٱلْعَذَابِ"},{"sura":23,"aya":64,"word_idxs":[5],"glyph":"ﮇ","uthmani":"إِذَا"},{"sura":23,"aya":64,"word_idxs":[6],"glyph":"ﮈ","uthmani":"هُمْ"},{"sura":23,"aya":64,"word_idxs":[7],"glyph":"ﮉ","uthmani":"يَجْـَٔرُونَ"}]},{"line":6,"type":"ayah","centered":false,"words":[{"sura":23,"aya":64,"word_idxs":[],"glyph":"ﮊ","uthmani":""},{"sura":23,"aya":65,"word_idxs":[0],"glyph":"ﮋ","uthmani":"لَا"},{"sura":23,"aya":65,"word_idxs":[1],"glyph":"ﮌ","uthmani":"تَجْـَٔرُوا۟"},{"sura":23,"aya":65,"word_idxs":[2],"glyph":"ﮍﮎ","uthmani":"ٱلْيَوْمَ"},{"sura":23,"aya":65,"word_idxs":[3],"glyph":"ﮏ","uthmani":"إِنَّكُم"},{"sura":23,"aya":65,"word_idxs":[4],"glyph":"ﮐ","uthmani":"مِّنَّا"},{"sura":23,"aya":65,"word_idxs":[5],"glyph":"ﮑ","uthmani":"لَا"},{"sura":23,"aya":65,"word_idxs":[6],"glyph":"ﮒ","uthmani":"تُنصَرُونَ"},{"sura":23,"aya":65,"word_idxs":[],"glyph":"ﮓ","uthmani":""},{"sura":23,"aya":66,"word_idxs":[0],"glyph":"ﮔ","uthmani":"قَدْ"},{"sura":23,"aya":66,"word_idxs":[1],"glyph":"ﮕ","uthmani":"كَانَتْ"},{"sura":23,"aya":66,"word_idxs":[2],"glyph":"ﮖ","uthmani":"ءَايَـٰتِى"}]},{"line":7,"type":"ayah","centered":false,"words":[{"sura":23,"aya":66,"word_idxs":[3],"glyph":"ﮗ","uthmani":"تُتْلَىٰ"},{"sura":23,"aya":66,"word_idxs":[4],"glyph":"ﮘ","uthmani":"عَلَيْكُمْ"},{"sura":23,"aya":66,"word_idxs":[5],"glyph":"ﮙ","uthmani":"فَكُنتُمْ"},{"sura":23,"aya":66,"word_idxs":[6],"glyph":"ﮚ","uthmani":"عَلَىٰٓ"},{"sura":23,"aya":66,"word_idxs":[7],"glyph":"ﮛ","uthmani":"أَعْقَـٰبِكُمْ"},{"sura":23,"aya":66,"word_idxs":[8],"glyph":"ﮜ","uthmani":"تَنكِصُونَ"},{"sura":23,"aya":66,"word_idxs":[],"glyph":"ﮝ","uthmani":""},{"sura":23,"aya":67,"word_idxs":[0],"glyph":"ﮞ","uthmani":"مُسْتَكْبِرِينَ"}]},{"line":8,"type":"ayah","centered":false,"words":[{"sura":23,"aya":67,"word_idxs":[1],"glyph":"ﮟ","uthmani":"بِهِۦ"},{"sura":23,"aya":67,"word_idxs":[2],"glyph":"ﮠ","uthmani":"سَـٰمِرًۭا"},{"sura":23,"aya":67,"word_idxs":[3],"glyph":"ﮡ","uthmani":"تَهْجُرُونَ"},{"sura":23,"aya":67,"word_idxs":[],"glyph":"ﮢ","uthmani":""},{"sura":23,"aya":68,"word_idxs":[0],"glyph":"ﮣ","uthmani":"أَفَلَمْ"},{"sura":23,"aya":68,"word_idxs":[1],"glyph":"ﮤ","uthmani":"يَدَّبَّرُوا۟"},{"sura":23,"aya":68,"word_idxs":[2],"glyph":"ﮥ","uthmani":"ٱلْقَوْلَ"},{"sura":23,"aya":68,"word_idxs":[3],"glyph":"ﮦ","uthmani":"أَمْ"},{"sura":23,"aya":68,"word_idxs":[4],"glyph":"ﮧ","uthmani":"جَآءَهُم"},{"sura":23,"aya":68,"word_idxs":[5],"glyph":"ﮨ","uthmani":"مَّا"},{"sura":23,"aya":68,"word_idxs":[6],"glyph":"ﮩ","uthmani":"لَمْ"},{"sura":23,"aya":68,"word_idxs":[7],"glyph":"ﮪ","uthmani":"يَأْتِ"}]},{"line":9,"type":"ayah","centered":false,"words":[{"sura":23,"aya":68,"word_idxs":[8],"glyph":"ﮫ","uthmani":"ءَابَآءَهُمُ"},{"sura":23,"aya":68,"word_idxs":[9],"glyph":"ﮬ","uthmani":"ٱلْأَوَّلِينَ"},{"sura":23,"aya":68,"word_idxs":[],"glyph":"ﮭ","uthmani":""},{"sura":23,"aya":69,"word_idxs":[0],"glyph":"ﮮ","uthmani":"أَمْ"},{"sura":23,"aya":69,"word_idxs":[1],"glyph":"ﮯ","uthmani":"لَمْ"},{"sura":23,"aya":69,"word_idxs":[2],"glyph":"ﮰ","uthmani":"يَعْرِفُوا۟"},{"sura":23,"aya":69,"word_idxs":[3],"glyph":"ﮱ","uthmani":"رَسُولَهُمْ"},{"sura":23,"aya":69,"word_idxs":[4],"glyph":"ﯓ","uthmani":"فَهُمْ"},{"sura":23,"aya":69,"word_idxs":[5],"glyph":"ﯔ","uthmani":"لَهُۥ"},{"sura":23,"aya":69,"word_idxs":[6],"glyph":"ﯕ","uthmani":"مُنكِرُونَ"}]},{"line":10,"type":"ayah","centered":false,"words":[{"sura":23,"aya":69,"word_idxs":[],"glyph":"ﯖ","uthmani":""},{"sura":23,"aya":70,"word_idxs":[0],"glyph":"ﯗ","uthmani":"أَمْ"},{"sura":23,"aya":70,"word_idxs":[1],"glyph":"ﯘ","uthmani":"يَقُولُونَ"},{"sura":23,"aya":70,"word_idxs":[2],"glyph":"ﯙ","uthmani":"بِهِۦ"},{"sura":23,"aya":70,"word_idxs":[3],"glyph":"ﯚﯛ","uthmani":"جِنَّةٌۢ"},{"sura":23,"aya":70,"word_idxs":[4],"glyph":"ﯜ","uthmani":"بَلْ"},{"sura":23,"aya":70,"word_idxs":[5],"glyph":"ﯝ","uthmani":"جَآءَهُم"},{"sura":23,"aya":70,"word_idxs":[6],"glyph":"ﯞ","uthmani":"بِٱلْحَقِّ"},{"sura":23,"aya":70,"word_idxs":[7],"glyph":"ﯟ","uthmani":"وَأَكْثَرُهُمْ"},{"sura":23,"aya":70,"word_idxs":[8],"glyph":"ﯠ","uthmani":"لِلْحَقِّ"}]},{"line":11,"type":"ayah","centered":false,"words":[{"sura":23,"aya":70,"word_idxs":[9],"glyph":"ﯡ","uthmani":"كَـٰرِهُونَ"},{"sura":23,"aya":70,"word_idxs":[],"glyph":"ﯢ","uthmani":""},{"sura":23,"aya":71,"word_idxs":[0],"glyph":"ﯣ","uthmani":"وَلَوِ"},{"sura":23,"aya":71,"word_idxs":[1],"glyph":"ﯤ","uthmani":"ٱتَّبَعَ"},{"sura":23,"aya":71,"word_idxs":[2],"glyph":"ﯥ","uthmani":"ٱلْحَقُّ"},{"sura":23,"aya":71,"word_idxs":[3],"glyph":"ﯦ","uthmani":"أَهْوَآءَهُمْ"},{"sura":23,"aya":71,"word_idxs":[4],"glyph":"ﯧ","uthmani":"لَفَسَدَتِ"},{"sura":23,"aya":71,"word_idxs":[5],"glyph":"ﯨ","uthmani":"ٱلسَّمَـٰوَٰتُ"}]},{"line":12,"type":"ayah","centered":false,"words":[{"sura":23,"aya":71,"word_idxs":[6],"glyph":"ﯩ","uthmani":"وَٱلْأَرْضُ"},{"sura":23,"aya":71,"word_idxs":[7],"glyph":"ﯪ","uthmani":"وَمَن"},{"sura":23,"aya":71,"word_idxs":[8],"glyph":"ﯫﯬ","uthmani":"فِيهِنَّ"},{"sura":23,"aya":71,"word_idxs":[9],"glyph":"ﯭ","uthmani":"بَلْ"},{"sura":23,"aya":71,"word_idxs":[10],"glyph":"ﯮ","uthmani":"أَتَيْنَـٰهُم"},{"sura":23,"aya":71,"word_idxs":[11],"glyph":"ﯯ","uthmani":"بِذِكْرِهِمْ"},{"sura":23,"aya":71,"word_idxs":[12],"glyph":"ﯰ","uthmani":"فَهُمْ"},{"sura":23,"aya":71,"word_idxs":[13],"glyph":"ﯱ","uthmani":"عَن"}]},{"line":13,"type":"ayah","centered":false,"words":[{"sura":23,"aya":71,"word_idxs":[14],"glyph":"ﯲ","uthmani":"ذِكْرِهِم"},{"sura":23,"aya":71,"word_idxs":[15],"glyph":"ﯳ","uthmani":"مُّعْرِضُونَ"},{"sura":23,"aya":71,"word_idxs":[],"glyph":"ﯴ","uthmani":""},{"sura":23,"aya":72,"word_idxs":[0],"glyph":"ﯵ","uthmani":"أَمْ"},{"sura":23,"aya":72,"word_idxs":[1],"glyph":"ﯶ","uthmani":"تَسْـَٔلُهُمْ"},{"sura":23,"aya":72,"word_idxs":[2],"glyph":"ﯷ","uthmani":"خَرْجًۭا"},{"sura":23,"aya":72,"word_idxs":[3],"glyph":"ﯸ","uthmani":"فَخَرَاجُ"},{"sura":23,"aya":72,"word_idxs":[4],"glyph":"ﯹ","uthmani":"رَبِّكَ"},{"sura":23,"aya":72,"word_idxs":[5],"glyph":"ﯺﯻ","uthmani":"خَيْرٌۭ"}]},{"line":14,"type":"ayah","centered":false,"words":[{"sura":23,"aya":72,"word_idxs":[6],"glyph":"ﯼ","uthmani":"وَهُوَ"},{"sura":23,"aya":72,"word_idxs":[7],"glyph":"ﯽ","uthmani":"خَيْرُ"},{"sura":23,"aya":72,"word_idxs":[8],"glyph":"ﯾ","uthmani":"ٱلرَّٰزِقِينَ"},{"sura":23,"aya":72,"word_idxs":[],"glyph":"ﯿ","uthmani":""},{"sura":23,"aya":73,"word_idxs":[0],"glyph":"ﰀ","uthmani":"وَإِنَّكَ"},{"sura":23,"aya":73,"word_idxs":[1],"glyph":"ﰁ","uthmani":"لَتَدْعُوهُمْ"},{"sura":23,"aya":73,"word_idxs":[2],"glyph":"ﰂ","uthmani":"إِلَىٰ"},{"sura":23,"aya":73,"word_idxs":[3],"glyph":"ﰃ","uthmani":"صِرَٰطٍۢ"},{"sura":23,"aya":73,"word_idxs":[4],"glyph":"ﰄ","uthmani":"مُّسْتَقِيمٍۢ"},{"sura":23,"aya":73,"word_idxs":[],"glyph":"ﰅ","uthmani":""}]},{"line":15,"type":"ayah","centered":false,"words":[{"sura":23,"aya":74,"word_idxs":[0],"glyph":"ﰆ","uthmani":"وَإِنَّ"},{"sura":23,"aya":74,"word_idxs":[1],"glyph":"ﰇ","uthmani":"ٱلَّذِينَ"},{"sura":23,"aya":74,"word_idxs":[2],"glyph":"ﰈ","uthmani":"لَا"},{"sura":23,"aya":74,"word_idxs":[3],"glyph":"ﰉ","uthmani":"يُؤْمِنُونَ"},{"sura":23,"aya":74,"word_idxs":[4],"glyph":"ﰊ","uthmani":"بِٱلْـَٔاخِرَةِ"},{"sura":23,"aya":74,"word_idxs":[5],"glyph":"ﰋ","uthmani":"عَنِ"},{"sura":23,"aya":74,"word_idxs":[6],"glyph":"ﰌ","uthmani":"ٱلصِّرَٰطِ"},{"sura":23,"aya":74,"word_idxs":[7],"glyph":"ﰍ","uthmani":"لَنَـٰكِبُونَ"},{"sura":23,"aya":74,"word_idxs":[],"glyph":"ﰎ","uthmani":""}]}],"suras":[23]}