{"page":520,"lines":[{"line":1,"type":"ayah","centered":false,"words":[{"sura":50,"aya":36,"word_idxs":[0],"glyph":"ﭑ","uthmani":"وَكَمْ"},{"sura":50,"aya":36,"word_idxs":[1],"glyph":"ﭒ","uthmani":"أَهْلَكْنَا"},{"sura":50,"aya":36,"word_idxs":[2],"glyph":"ﭓ","uthmani":"قَبْلَهُم"},{"sura":50,"aya":36,"word_idxs":[3],"glyph":"ﭔ","uthmani":"مِّن"},{"sura":50,"aya":36,"word_idxs":[4],"glyph":"ﭕ","uthmani":"قَرْنٍ"},{"sura":50,"aya":36,"word_idxs":[5],"glyph":"ﭖ","uthmani":"هُمْ"},{"sura":50,"aya":36,"word_idxs":[6],"glyph":"ﭗ","uthmani":"أَشَدُّ"},{"sura":50,"aya":36,"word_idxs":[7],"glyph":"ﭘ","uthmani":"مِنْهُم"},{"sura":50,"aya":36,"word_idxs":[8],"glyph":"ﭙ","uthmani":"بَطْشًۭا"},{"sura":50,"aya":36,"word_idxs":[9],"glyph":"ﭚ","uthmani":"فَنَقَّبُوا۟"},{"sura":50,"aya":36,"word_idxs":[10],"glyph":"ﭛ","uthmani":"فِى"}]},{"line":2,"type":"ayah","centered":false,"words":[{"sura":50,"aya":36,"word_idxs":[11],"glyph":"ﭜ","uthmani":"ٱلْبِلَـٰدِ"},{"sura":50,"aya":36,"word_idxs":[12],"glyph":"ﭝ","uthmani":"هَلْ"},{"sura":50,"aya":36,"word_idxs":[13],"glyph":"ﭞ","uthmani":"مِن"},{"sura":50,"aya":36,"word_idxs":[14],"glyph":"ﭟ","uthmani":"مَّحِيصٍ"},{"sura":50,"aya":36,"word_idxs":[],"glyph":"ﭠ","uthmani":""},{"sura":50,"aya":37,"word_idxs":[0],"glyph":"ﭡ","uthmani":"إِنَّ"},{"sura":50,"aya":37,"word_idxs":[1],"glyph":"ﭢ","uthmani":"فِى"},{"sura":50,"aya":37,"word_idxs":[2],"glyph":"ﭣ","uthmani":"ذَٰلِكَ"},{"sura":50,"aya":37,"word_idxs":[3],"glyph":"ﭤ","uthmani":"لَذِكْرَىٰ"},{"sura":50,"aya":37,"word_idxs":[4],"glyph":"ﭥ","uthmani":"لِمَن"},{"sura":50,"aya":37,"word_idxs":[5],"glyph":"ﭦ","uthmani":"كَانَ"}]},{"line":3,"type":"ayah","centered":false,"words":[{"sura":50,"aya":37,"word_idxs":[6],"glyph":"ﭧ","uthmani":"لَهُۥ"},{"sura":50,"aya":37,"word_idxs":[7],"glyph":"ﭨ","uthmani":"قَلْبٌ"},{"sura":50,"aya":37,"word_idxs":[8],"glyph":"ﭩ","uthmani":"أَوْ"},{"sura":50,"aya":37,"word_idxs":[9],"glyph":"ﭪ","uthmani":"أَلْقَى"},{"sura":50,"aya":37,"word_idxs":[10],"glyph":"ﭫ","uthmani":"ٱلسَّمْعَ"},{"sura":50,"aya":37,"word_idxs":[11],"glyph":"ﭬ","uthmani":"وَهُوَ"},{"sura":50,"aya":37,"word_idxs":[12],"glyph":"ﭭ","uthmani":"شَهِيدٌۭ"},{"sura":50,"aya":37,"word_idxs":[],"glyph":"ﭮ","uthmani":""},{"sura":50,"aya":38,"word_idxs":[0],"glyph":"ﭯ","uthmani":"وَلَقَدْ"},{"sura":50,"aya":38,"word_idxs":[1],"glyph":"ﭰ","uthmani":"خَلَقْنَا"}]},{"line":4,"type":"ayah","centered":false,"words":[{"sura":50,"aya":38,"word_idxs":[2],"glyph":"ﭱ","uthmani":"ٱلسَّمَـٰوَٰتِ"},{"sura":50,"aya":38,"word_idxs":[3],"glyph":"ﭲ","uthmani":"وَٱلْأَرْضَ"},{"sura":50,"aya":38,"word_idxs":[4],"glyph":"ﭳ","uthmani":"وَمَا"},{"sura":50,"aya":38,"word_idxs":[5],"glyph":"ﭴ","uthmani":"بَيْنَهُمَا"},{"sura":50,"aya":38,"word_idxs":[6],"glyph":"ﭵ","uthmani":"فِى"},{"sura":50,"aya":38,"word_idxs":[7],"glyph":"ﭶ","uthmani":"سِتَّةِ"},{"sura":50,"aya":38,"word_idxs":[8],"glyph":"ﭷ","uthmani":"أَيَّامٍۢ"},{"sura":50,"aya":38,"word_idxs":[9],"glyph":"ﭸ","uthmani":"وَمَا"},{"sura":50,"aya":38,"word_idxs":[10],"glyph":"ﭹ","uthmani":"مَسَّنَا"}]},{"line":5,"type":"ayah","centered":false,"words":[{"sura":50,"aya":38,"word_idxs":[11],"glyph":"ﭺ","uthmani":"مِن"},{"sura":50,"aya":38,"word_idxs":[12],"glyph":"ﭻ","uthmani":"لُّغُوبٍۢ"},{"sura":50,"aya":38,"word_idxs":[],"glyph":"ﭼ","uthmani":""},{"sura":50,"aya":39,"word_idxs":[0],"glyph":"ﭽ","uthmani":"فَٱصْبِرْ"},{"sura":50,"aya":39,"word_idxs":[1],"glyph":"ﭾ","uthmani":"عَلَىٰ"},{"sura":50,"aya":39,"word_idxs":[2],"glyph":"ﭿ","uthmani":"مَا"},{"sura":50,"aya":39,"word_idxs":[3],"glyph":"ﮀ","uthmani":"يَقُولُونَ"},{"sura":50,"aya":39,"word_idxs":[4],"glyph":"ﮁ","uthmani":"وَسَبِّحْ"},{"sura":50,"aya":39,"word_idxs":[5],"glyph":"ﮂ","uthmani":"بِحَمْدِ"},{"sura":50,"aya":39,"word_idxs":[6],"glyph":"ﮃ","uthmani":"رَبِّكَ"}]},{"line":6,"type":"ayah","centered":false,"words":[{"sura":50,"aya":39,"word_idxs":[7],"glyph":"ﮄ","uthmani":"قَبْلَ"},{"sura":50,"aya":39,"word_idxs":[8],"glyph":"ﮅ","uthmani":"طُلُوعِ"},{"sura":50,"aya":39,"word_idxs":[9],"glyph":"ﮆ","uthmani":"ٱلشَّمْسِ"},{"sura":50,"aya":39,"word_idxs":[10],"glyph":"ﮇ","uthmani":"وَقَبْلَ"},{"sura":50,"aya":39,"word_idxs":[11],"glyph":"ﮈ","uthmani":"ٱلْغُرُوبِ"},{"sura":50,"aya":39,"word_idxs":[],"glyph":"ﮉ","uthmani":""},{"sura":50,"aya":40,"word_idxs":[0],"glyph":"ﮊ","uthmani":"وَمِنَ"},{"sura":50,"aya":40,"word_idxs":[1],"glyph":"ﮋ","uthmani":"ٱلَّيْلِ"},{"sura":50,"aya":40,"word_idxs":[2],"glyph":"ﮌ","uthmani":"فَسَبِّحْهُ"}]},{"line":7,"type":"ayah","centered":false,"words":[{"sura":50,"aya":40,"word_idxs":[3],"glyph":"ﮍ","uthmani":"وَأَدْبَـٰرَ"},{"sura":50,"aya":40,"word_idxs":[4],"glyph":"ﮎ","uthmani":"ٱلسُّجُودِ"},{"sura":50,"aya":40,"word_idxs":[],"glyph":"ﮏ","uthmani":""},{"sura":50,"aya":41,"word_idxs":[0],"glyph":"ﮐ","uthmani":"وَٱسْتَمِعْ"},{"sura":50,"aya":41,"word_idxs":[1],"glyph":"ﮑ","uthmani":"يَوْمَ"},{"sura":50,"aya":41,"word_idxs":[2],"glyph":"ﮒ","uthmani":"يُنَادِ"},{"sura":50,"aya":41,"word_idxs":[3],"glyph":"ﮓ","uthmani":"ٱلْمُنَادِ"},{"sura":50,"aya":41,"word_idxs":[4],"glyph":"ﮔ","uthmani":"مِن"},{"sura":50,"aya":41,"word_idxs":[5],"glyph":"ﮕ","uthmani":"مَّكَانٍۢ"},{"sura":50,"aya":41,"word_idxs":[6],"glyph":"ﮖ","uthmani":"قَرِيبٍۢ"}]},{"line":8,"type":"ayah","centered":false,"words":[{"sura":50,"aya":41,"word_idxs":[],"glyph":"ﮗ","uthmani":""},{"sura":50,"aya":42,"word_idxs":[0],"glyph":"ﮘ","uthmani":"يَوْمَ"},{"sura":50,"aya":42,"word_idxs":[1],"glyph":"ﮙ","uthmani":"يَسْمَعُونَ"},{"sura":50,"aya":42,"word_idxs":[2],"glyph":"ﮚ","uthmani":"ٱلصَّيْحَةَ"},{"sura":50,"aya":42,"word_idxs":[3],"glyph":"ﮛﮜ","uthmani":"بِٱلْحَقِّ"},{"sura":50,"aya":42,"word_idxs":[4],"glyph":"ﮝ","uthmani":"ذَٰلِكَ"},{"sura":50,"aya":42,"word_idxs":[5],"glyph":"ﮞ","uthmani":"يَوْمُ"},{"sura":50,"aya":42,"word_idxs":[6],"glyph":"ﮟ","uthmani":"ٱلْخُرُوجِ"},{"sura":50,"aya":42,"word_idxs":[],"glyph":"ﮠ","uthmani":""},{"sura":50,"aya":43,"word_idxs":[0],"glyph":"ﮡ","uthmani":"إِنَّا"}]},{"line":9,"type":"ayah","centered":false,"words":[{"sura":50,"aya":43,"word_idxs":[1],"glyph":"ﮢ","uthmani":"نَحْنُ"},{"sura":50,"aya":43,"word_idxs":[2],"glyph":"ﮣ","uthmani":"نُحْىِۦ"},{"sura":50,"aya":43,"word_idxs":[3],"glyph":"ﮤ","uthmani":"وَنُمِيتُ"},{"sura":50,"aya":43,"word_idxs":[4],"glyph":"ﮥ","uthmani":"وَإِلَيْنَا"},{"sura":50,"aya":43,"word_idxs":[5],"glyph":"ﮦ","uthmani":"ٱلْمَصِيرُ"},{"sura":50,"aya":43,"word_idxs":[],"glyph":"ﮧ","uthmani":""},{"sura":50,"aya":44,"word_idxs":[0],"glyph":"ﮨ","uthmani":"يَوْمَ"},{"sura":50,"aya":44,"word_idxs":[1],"glyph":"ﮩ","uthmani":"تَشَقَّقُ"},{"sura":50,"aya":44,"word_idxs":[2],"glyph":"ﮪ","uthmani":"ٱلْأَرْضُ"}]},{"line":10,"type":"ayah","centered":false,"words":[{"sura":50,"aya":44,"word_idxs":[3],"glyph":"ﮫ","uthmani":"عَنْهُمْ"},{"sura":50,"aya":44,"word_idxs":[4],"glyph":"ﮬﮭ","uthmani":"سِرَاعًۭا"},{"sura":50,"aya":44,"word_idxs":[5],"glyph":"ﮮ","uthmani":"ذَٰلِكَ"},{"sura":50,"aya":44,"word_idxs":[6],"glyph":"ﮯ","uthmani":"حَشْرٌ"},{"sura":50,"aya":44,"word_idxs":[7],"glyph":"ﮰ","uthmani":"عَلَيْنَا"},{"sura":50,"aya":44,"word_idxs":[8],"glyph":"ﮱ","uthmani":"يَسِيرٌۭ"},{"sura":50,"aya":44,"word_idxs":[],"glyph":"ﯓ","uthmani":""},{"sura":50,"aya":45,"word_idxs":[0],"glyph":"ﯔ","uthmani":"نَّحْنُ"},{"sura":50,"aya":45,"word_idxs":[1],"glyph":"ﯕ","uthmani":"أَعْلَمُ"},{"sura":50,"aya":45,"word_idxs":[2],"glyph":"ﯖ","uthmani":"بِمَا"},{"sura":50,"aya":45,"word_idxs":[3],"glyph":"ﯗﯘ","uthmani":"يَقُولُونَ"}]},{"line":11,"type":"ayah","centered":false,"words":[{"sura":50,"aya":45,"word_idxs":[4],"glyph":"ﯙ","uthmani":"وَمَآ"},{"sura":50,"aya":45,"word_idxs":[5],"glyph":"ﯚ","uthmani":"أَنتَ"},{"sura":50,"aya":45,"word_idxs":[6],"glyph":"ﯛ","uthmani":"عَلَيْهِم"},{"sura":50,"aya":45,"word_idxs":[7],"glyph":"ﯜﯝ","uthmani":"بِجَبَّارٍۢ"},{"sura":50,"aya":45,"word_idxs":[8],"glyph":"ﯞ","uthmani":"فَذَكِّرْ"},{"sura":50,"aya":45,"word_idxs":[9],"glyph":"ﯟ","uthmani":"بِٱلْقُرْءَانِ"},{"sura":50,"aya":45,"word_idxs":[10],"glyph":"ﯠ","uthmani":"مَن"},{"sura":50,"aya":45,"word_idxs":[11],"glyph":"ﯡ","uthmani":"يَخَافُ"},{"sura":50,"aya":45,"word_idxs":[12],"glyph":"ﯢ","uthmani":"وَعِيدِ"},{"sura":50,"aya":45,"word_idxs":[],"glyph":"ﯣ","uthmani":""}]},{"line":12,"type":"surah_name","centered":true,"surah":51,"words":[]},{"line":13,"type":"basmallah","centered":true,"words":[]},{"line":14,"type":"ayah","centered":false,"words":[{"sura":51,"aya":1,"word_idxs":[0],"glyph":"ﯤ","uthmani":"وَٱلذَّٰرِيَـٰتِ"},{"sura":51,"aya":1,"word_idxs":[1],"glyph":"ﯥ","uthmani":"ذَرْوًۭا"},{"sura":51,"aya":1,"word_idxs":[],"glyph":"ﯦ","uthmani":""},{"sura":51,"aya":2,"word_idxs":[0],"glyph":"ﯧ","uthmani":"فَٱلْحَـٰمِلَـٰتِ"},{"sura":51,"aya":2,"word_idxs":[1],"glyph":"ﯨ","uthmani":"وِقْرًۭا"},{"sura":51,"aya":2,"word_idxs":[],"glyph":"ﯩ","uthmani":""},{"sura":51,"aya":3,"word_idxs":[0],"glyph":"ﯪ","uthmani":"فَٱلْجَـٰرِيَـٰتِ"},{"sura":51,"aya":3,"word_idxs":[1],"glyph":"ﯫ","uthmani":"يُسْرًۭا"},{"sura":51,"aya":3,"word_idxs":[],"glyph":"ﯬ","uthmani":""}]},{"line":15,"type":"ayah","centered":false,"words":[{"sura":51,"aya":4,"word_idxs":[0],"glyph":"ﯭ","uthmani":"فَٱلْمُقَسِّمَـٰتِ"},{"sura":51,"aya":4,"word_idxs":[1],"glyph":"ﯮ","uthmani":"أَمْرًا"},{"sura":51,"aya":4,"word_idxs":[],"glyph":"ﯯ","uthmani":""},{"sura":51,"aya":5,"word_idxs":[0],"glyph":"ﯰ","uthmani":"إِنَّمَا"},{"sura":51,"aya":5,"word_idxs":[1],"glyph":"ﯱ","uthmani":"تُوعَدُونَ"},{"sura":51,"aya":5,"word_idxs":[2],"glyph":"ﯲ","uthmani":"لَصَادِقٌۭ"},{"sura":51,"aya":5,"word_idxs":[],"glyph":"ﯳ","uthmani":""},{"sura":51,"aya":6,"word_idxs":[0],"glyph":"ﯴ","uthmani":"وَإِنَّ"},{"sura":51,"aya":6,"word_idxs":[1],"glyph":"ﯵ","uthmani":"ٱلدِّينَ"},{"sura":51,"aya":6,"word_idxs":[2],"glyph":"ﯶ","uthmani":"لَوَٰقِعٌۭ"},{"sura":51,"aya":6,"word_idxs":[],"glyph":"ﯷ","uthmani":""}]}],"suras":[50,51]}